ProgettiHWSW/ProgettiHWSWAPI.py
ProgettiHWSW/__init__.py
ProgettiHWSW/analog.py
ProgettiHWSW/api.py
ProgettiHWSW/const.py
ProgettiHWSW/input.py
ProgettiHWSW/relay.py
ProgettiHWSW/temperature.py
ProgettiHWSW-0.1.2.dist-info/LICENSE
ProgettiHWSW-0.1.2.dist-info/METADATA
ProgettiHWSW-0.1.2.dist-info/WHEEL
ProgettiHWSW-0.1.2.dist-info/top_level.txt
ProgettiHWSW-0.1.2.dist-info/RECORD
