Metadata-Version: 2.1
Name: ProgettiHWSW
Version: 0.1.2
Summary: Controls ProgettiHWSW relay boards.
Home-page: http://github.com/ardaseremet/progettihwsw
Author: Arda Seremet
Author-email: ardaseremet@outlook.com
License: MIT
Download-URL: http://github.com/ardaseremet/progettihwsw/tarball/0.1.2
Platform: UNKNOWN
Classifier: License :: OSI Approved :: MIT License
Classifier: Development Status :: 5 - Production/Stable
Classifier: Programming Language :: Python :: 3.7
Classifier: Programming Language :: Python :: 3.8
Classifier: Intended Audience :: Telecommunications Industry
Classifier: Intended Audience :: Information Technology
Classifier: Intended Audience :: End Users/Desktop
Classifier: Intended Audience :: Legal Industry
Requires-Dist: aiohttp
Requires-Dist: lxml
